django_identity/__init__.py
django_identity/admin.py
django_identity/apps.py
django_identity/migrations/__init__.py
django_identity/models.py
django_identity/tests.py
django_identity/views.py
django_identity-0.1.0.dist-info/METADATA
django_identity-0.1.0.dist-info/WHEEL
django_identity-0.1.0.dist-info/RECORD
