Metadata-Version: 2.3
Name: django-identity
Version: 0.1.0
Summary: Development in progress - please come back later.
Author: Stacy Noland
Author-email: 46572585+stacynoland@users.noreply.github.com
Requires-Python: >=3.13
Classifier: Programming Language :: Python :: 3
Classifier: Programming Language :: Python :: 3.13
Requires-Dist: django (>=5.1.7,<6.0.0)
